mypy1989/__init__.py
mypy1989/add.py
mypy1989/subtract.py
mypy1989/more/__init__.py
mypy1989/more/divide.py
mypy1989/more/multiply.py
mypy1989-0.0.2.dist-info/LICENSE
mypy1989-0.0.2.dist-info/METADATA
mypy1989-0.0.2.dist-info/WHEEL
mypy1989-0.0.2.dist-info/top_level.txt
mypy1989-0.0.2.dist-info/RECORD
